sneko/__init__.py
sneko/__main__.py
sneko/app.py
sneko/config.py
sneko/main.tcss
sneko/solidity.scm
sneko/utils.py
sneko/vyper.scm
sneko/contracts/solidity/Blank.sol
sneko/contracts/solidity/NumberStore.sol
sneko/contracts/solidity/PopupFaucet.sol
sneko/contracts/solidity/SnekoToken.sol
sneko/contracts/solidity/OpenZeppelin/v5.0.2/access/AccessControl.sol
sneko/contracts/solidity/OpenZeppelin/v5.0.2/access/IAccessControl.sol
sneko/contracts/solidity/OpenZeppelin/v5.0.2/access/Ownable.sol
sneko/contracts/solidity/OpenZeppelin/v5.0.2/access/Ownable2Step.sol
sneko/contracts/solidity/OpenZeppelin/v5.0.2/access/extensions/AccessControlDefaultAdminRules.sol
sneko/contracts/solidity/OpenZeppelin/v5.0.2/access/extensions/AccessControlEnumerable.sol
sneko/contracts/solidity/OpenZeppelin/v5.0.2/access/extensions/IAccessControlDefaultAdminRules.sol
sneko/contracts/solidity/OpenZeppelin/v5.0.2/access/extensions/IAccessControlEnumerable.sol
sneko/contracts/solidity/OpenZeppelin/v5.0.2/access/manager/AccessManaged.sol
sneko/contracts/solidity/OpenZeppelin/v5.0.2/access/manager/AccessManager.sol
sneko/contracts/solidity/OpenZeppelin/v5.0.2/access/manager/AuthorityUtils.sol
sneko/contracts/solidity/OpenZeppelin/v5.0.2/access/manager/IAccessManaged.sol
sneko/contracts/solidity/OpenZeppelin/v5.0.2/access/manager/IAccessManager.sol
sneko/contracts/solidity/OpenZeppelin/v5.0.2/access/manager/IAuthority.sol
sneko/contracts/solidity/OpenZeppelin/v5.0.2/finance/VestingWallet.sol
sneko/contracts/solidity/OpenZeppelin/v5.0.2/governance/Governor.sol
sneko/contracts/solidity/OpenZeppelin/v5.0.2/governance/IGovernor.sol
sneko/contracts/solidity/OpenZeppelin/v5.0.2/governance/TimelockController.sol
sneko/contracts/solidity/OpenZeppelin/v5.0.2/governance/extensions/GovernorCountingSimple.sol
sneko/contracts/solidity/OpenZeppelin/v5.0.2/governance/extensions/GovernorPreventLateQuorum.sol
sneko/contracts/solidity/OpenZeppelin/v5.0.2/governance/extensions/GovernorSettings.sol
sneko-0.1.5.dist-info/METADATA
sneko-0.1.5.dist-info/WHEEL
sneko-0.1.5.dist-info/entry_points.txt
sneko-0.1.5.dist-info/RECORD
