Metadata-Version: 2.3
Name: sneko
Version: 0.1.5
Summary: Terminal GUI for Ethereum smart contracts
Author-email: Marc Garreau <marc@ethereum.org>
Requires-Python: >=3.10
Requires-Dist: eth-tester>=0.12.0b1
Requires-Dist: py-evm>=0.10.1b1
Requires-Dist: py-solc-x
Requires-Dist: pyperclip
Requires-Dist: snekmate>=0.1.0
Requires-Dist: textual[syntax]>=0.85.1
Requires-Dist: tree-sitter-types==0.0.2
Requires-Dist: tree-sitter>=0.20.1
Requires-Dist: vyper==0.4.0
Requires-Dist: web3>=7.4.0
